gcloud_storage_api/__init__.py
gcloud_storage_api/Cloud31_Storage31.py
gcloud_storage_api-0.0.65.dist-info/DESCRIPTION.rst
gcloud_storage_api-0.0.65.dist-info/entry_points.txt
gcloud_storage_api-0.0.65.dist-info/METADATA
gcloud_storage_api-0.0.65.dist-info/metadata.json
gcloud_storage_api-0.0.65.dist-info/RECORD
gcloud_storage_api-0.0.65.dist-info/top_level.txt
gcloud_storage_api-0.0.65.dist-info/WHEEL
