Metadata-Version: 2.0
Name: gcloud-storage-api
Version: 0.0.65
Summary: gCloud - The Cloud made in Italy Python API
Home-page: http://gcloud.schema31.it
Author: Ilario Febi
Author-email: ifebi@schema31.it
License: BSD
Keywords: gcloud,schema31,Schema 31
Platform: UNKNOWN
Classifier: Development Status :: 3 - Alpha
Classifier: Intended Audience :: Developers
Classifier: Natural Language :: Italian
Classifier: License :: OSI Approved :: BSD License
Classifier: Operating System :: OS Independent
Classifier: Programming Language :: Python
Classifier: Programming Language :: Python :: 2
Classifier: Programming Language :: Python :: 2.7
Classifier: Programming Language :: Python :: 3
Classifier: Programming Language :: Python :: 3.4
Classifier: Environment :: Console
Requires-Dist: requests
Requires-Dist: argparse
